pydqt/__init__.py
pydqt/pydqt.py
pydqt/sql/templates/macros/macros.jinja
pydqt/test.csv
pydqt/tests/test_querying.py
pydqt/workspaces/main/templates/base.sql
pydqt/workspaces/main/templates/example.sql
pydqt-4.0.5.dist-info/METADATA
pydqt-4.0.5.dist-info/WHEEL
pydqt-4.0.5.dist-info/RECORD
