Metadata-Version: 2.1
Name: pydqt
Version: 4.0.5
Summary: A package to help parameterise and macrofy sql queries
Home-page: https://github.com/markingham77/dqt
License: MIT
Author: Mark Ingham
Author-email: mark.ingham@ly.st
Requires-Python: >=3.11,<3.13
Classifier: License :: OSI Approved :: MIT License
Classifier: Programming Language :: Python :: 3
Classifier: Programming Language :: Python :: 3.11
Requires-Dist: decouple (>=0.0.7,<0.0.8)
Requires-Dist: duckdb (<=0.8.1)
Requires-Dist: jinja2 (>=3.1.2,<4.0.0)
Requires-Dist: pandas (>=2.1.1,<3.0.0)
Requires-Dist: pytest (>=7.4.2,<8.0.0)
Requires-Dist: python-decouple (>=3.8,<4.0)
Requires-Dist: python-dotenv (>=1.0.0,<2.0.0)
Requires-Dist: snowflake-connector-python (>=3.3.1,<4.0.0)
Requires-Dist: sqlparse (>=0.4.4,<0.5.0)
Project-URL: Repository, https://github.com/markingham77/dqt
